[{"room": "\u6566\u5357 4 \u6559\u5ba4", "date": "04 Jul Mon", "href": "https://www.trueclassbooking.com.tw/member/popup/class-info.aspx?tcl_id=1076570", "name": "Vinyasa Yoga \u6d41\u66a2\u745c\u73c8", "teacher": "Una", "time": "10:30 - 11:30 AM"}, {"room": "\u6566\u5357 4 \u6559\u5ba4", "date": "04 Jul Mon", "href": "https://www.trueclassbooking.com.tw/member/popup/class-info.aspx?tcl_id=1076571", "name": "Flow Yoga \u52d5\u745c\u73c8", "teacher": "Ellen", "time": "12:15 - 01:15 PM"}, {"room": "\u6566\u5357 4 \u6559\u5ba4", "date": "04 Jul Mon", "href": "https://www.trueclassbooking.com.tw/member/popup/class-info.aspx?tcl_id=1076572", "name": "Hatha Yoga \u54c8\u9054\u745c\u73c8", "teacher": "Claire", "time": "02:15 - 03:15 PM"}, {"room": "\u6566\u5357 4 \u6559\u5ba4", "date": "04 Jul Mon", "href": "https://www.trueclassbooking.com.tw/member/popup/class-info.aspx?tcl_id=1076573", "name": "Ashtanga \u963f\u65af\u5766\u52a0 1", "teacher": "Ethan Lee", "time": "04:15 - 05:30 PM"}, {"room": "\u6566\u5357 4 \u6559\u5ba4", "date": "04 Jul Mon", "href": "https://www.trueclassbooking.com.tw/member/popup/class-info.aspx?tcl_id=1076574", "name": "Vinyasa Yoga \u6d41\u66a2\u745c\u73c8", "teacher": "Fly H.", "time": "07:30 - 08:30 PM"}, {"room": "\u6566\u5357 4 \u6559\u5ba4", "date": "04 Jul Mon", "href": "https://www.trueclassbooking.com.tw/member/popup/class-info.aspx?tcl_id=1076575", "name": "Gentle Stretch \u548c\u7de9\u4f38\u5c55", "teacher": "Andy Tenpa", "time": "09:00 - 10:00 PM"}, {"room": "\u6566\u5357 4 \u6559\u5ba4", "date": "05 Jul Tue", "href": "https://www.trueclassbooking.com.tw/member/popup/class-info.aspx?tcl_id=1076576", "name": "Yoga Wheel \u745c\u73c8\u8f2a", "teacher": "Simon Chang", "time": "09:30 - 10:30 AM"}, {"room": "\u6566\u5357 4 \u6559\u5ba4", "date": "05 Jul Tue", "href": "https://www.trueclassbooking.com.tw/member/popup/class-info.aspx?tcl_id=1077753", "name": "* \u5167\u90e8\u4f7f\u7528 *", "teacher": "(\u7279\u5225\u8b1b\u5e2b)", "time": "02:00 - 03:00 PM"}, {"room": "\u6566\u5357 4 \u6559\u5ba4", "date": "05 Jul Tue", "href": "https://www.trueclassbooking.com.tw/member/popup/class-info.aspx?tcl_id=1076642", "name": "Vinyasa Intro. \u6d41\u66a2\u745c\u73c8\u5165\u9580", "teacher": "Una", "time": "05:45 - 06:45 PM"}, {"room": "\u6566\u5357 4 \u6559\u5ba4", "date": "05 Jul Tue", "href": "https://www.trueclassbooking.com.tw/member/popup/class-info.aspx?tcl_id=1076643", "name": "Vinyasa Yoga2 \u6d41\u66a2\u745c\u73c8 2", "teacher": "Una", "time": "07:15 - 08:30 PM"}, {"room": "\u6566\u5357 4 \u6559\u5ba4", "date": "06 Jul Wed", "href": "https://www.trueclassbooking.com.tw/member/popup/class-info.aspx?tcl_id=1076581", "name": "Vinyasa Yoga \u6d41\u66a2\u745c\u73c8", "teacher": "Andy Tenpa", "time": "09:00 - 10:00 AM"}, {"room": "\u6566\u5357 4 \u6559\u5ba4", "date": "06 Jul Wed", "href": "https://www.trueclassbooking.com.tw/member/popup/class-info.aspx?tcl_id=1076582", "name": "Hatha Yoga \u54c8\u9054\u745c\u73c8", "teacher": "William L.", "time": "12:30 - 01:30 PM"}, {"room": "\u6566\u5357 4 \u6559\u5ba4", "date": "06 Jul Wed", "href": "https://www.trueclassbooking.com.tw/member/popup/class-info.aspx?tcl_id=1076646", "name": "GYROKINESIS\u00ae \u79aa\u67d4\u904b\u52d5", "teacher": "Pearl", "time": "03:30 - 04:30 PM"}, {"room": "\u6566\u5357 4 \u6559\u5ba4", "date": "06 Jul Wed", "href": "https://www.trueclassbooking.com.tw/member/popup/class-info.aspx?tcl_id=1076584", "name": "Hatha Yoga \u54c8\u9054\u745c\u73c8", "teacher": "Fly H.", "time": "06:00 - 07:00 PM"}, {"room": "\u6566\u5357 4 \u6559\u5ba4", "date": "06 Jul Wed", "href": "https://www.trueclassbooking.com.tw/member/popup/class-info.aspx?tcl_id=1076585", "name": "Gentle Yoga \u548c\u7de9\u745c\u73c8", "teacher": "Ellen", "time": "07:45 - 08:45 PM"}, {"room": "\u6566\u5357 4 \u6559\u5ba4", "date": "07 Jul Thu", "href": "https://www.trueclassbooking.com.tw/member/popup/class-info.aspx?tcl_id=1076586", "name": "\u6efe\u7b52\u7d9c\u5408\u8a13\u7df4", "teacher": "Jamie", "time": "09:00 - 10:00 AM"}, {"room": "\u6566\u5357 4 \u6559\u5ba4", "date": "07 Jul Thu", "href": "https://www.trueclassbooking.com.tw/member/popup/class-info.aspx?tcl_id=1076587", "name": "Vinyasa Intro \u6d41\u66a2\u745c\u73c8\u5165\u9580", "teacher": "Coco Wang", "time": "11:00 - 12:00 PM"}, {"room": "\u6566\u5357 4 \u6559\u5ba4", "date": "07 Jul Thu", "href": "https://www.trueclassbooking.com.tw/member/popup/class-info.aspx?tcl_id=1076588", "name": "Gentle Yoga \u548c\u7de9\u745c\u73c8", "teacher": "Simon Chang", "time": "04:30 - 05:30 PM"}, {"room": "\u6566\u5357 4 \u6559\u5ba4", "date": "07 Jul Thu", "href": "https://www.trueclassbooking.com.tw/member/popup/class-info.aspx?tcl_id=1076589", "name": "Yoga Tone", "teacher": "Una", "time": "06:00 - 07:00 PM"}, {"room": "\u6566\u5357 4 \u6559\u5ba4", "date": "07 Jul Thu", "href": "https://www.trueclassbooking.com.tw/member/popup/class-info.aspx?tcl_id=1076590", "name": "Gokul Yoga \u54c8\u9054\u745c\u73c8", "teacher": "Andy Tenpa", "time": "07:30 - 08:30 PM"}, {"room": "\u6566\u5357 4 \u6559\u5ba4", "date": "08 Jul Fri", "href": "https://www.trueclassbooking.com.tw/member/popup/class-info.aspx?tcl_id=1076591", "name": "Vinyasa Intro. \u6d41\u66a2\u745c\u73c8\u5165\u9580", "teacher": "Tumai", "time": "09:30 - 10:30 AM"}, {"room": "\u6566\u5357 4 \u6559\u5ba4", "date": "08 Jul Fri", "href": "https://www.trueclassbooking.com.tw/member/popup/class-info.aspx?tcl_id=1076592", "name": "Hatha Basic \u54c8\u9054\u57fa\u790e", "teacher": "Una", "time": "12:45 - 01:45 PM"}, {"room": "\u6566\u5357 4 \u6559\u5ba4", "date": "08 Jul Fri", "href": "https://www.trueclassbooking.com.tw/member/popup/class-info.aspx?tcl_id=1076593", "name": "Yoga Wheel \u745c\u73c8\u8f2a", "teacher": "Una", "time": "03:15 - 04:15 PM"}, {"room": "\u6566\u5357 4 \u6559\u5ba4", "date": "08 Jul Fri", "href": "https://www.trueclassbooking.com.tw/member/popup/class-info.aspx?tcl_id=1076594", "name": "Gentle Yoga \u548c\u7de9\u745c\u73c8", "teacher": "Ellen", "time": "04:30 - 05:30 PM"}, {"room": "\u6566\u5357 4 \u6559\u5ba4", "date": "08 Jul Fri", "href": "https://www.trueclassbooking.com.tw/member/popup/class-info.aspx?tcl_id=1076595", "name": "Gokul Yoga \u54c8\u9054\u745c\u73c8", "teacher": "Andy Tenpa", "time": "06:00 - 07:00 PM"}, {"room": "\u6566\u5357 4 \u6559\u5ba4", "date": "08 Jul Fri", "href": "https://www.trueclassbooking.com.tw/member/popup/class-info.aspx?tcl_id=1076596", "name": "Vinyasa Yoga \u6d41\u66a2\u745c\u73c8", "teacher": "Andy Tenpa", "time": "07:30 - 08:30 PM"}, {"room": "\u6566\u5357 4 \u6559\u5ba4", "date": "09 Jul Sat", "href": "https://www.trueclassbooking.com.tw/member/popup/class-info.aspx?tcl_id=1077581", "name": "*YE\u5718\u9ad4\u5c0f\u73ed*", "teacher": "Joyce", "time": "10:15 - 11:30 AM"}, {"room": "\u6566\u5357 4 \u6559\u5ba4", "date": "09 Jul Sat", "href": "https://www.trueclassbooking.com.tw/member/popup/class-info.aspx?tcl_id=1076599", "name": "Vinyasa Yoga \u6d41\u66a2\u745c\u73c8", "teacher": "Coco Wang", "time": "03:30 - 04:30 PM"}, {"room": "\u6566\u5357 4 \u6559\u5ba4", "date": "09 Jul Sat", "href": "https://www.trueclassbooking.com.tw/member/popup/class-info.aspx?tcl_id=1076600", "name": "GYROKINESIS\u00ae \u79aa\u67d4\u904b\u52d5 (B)", "teacher": "Pearl", "time": "05:30 - 06:30 PM"}, {"room": "\u6566\u5357 4 \u6559\u5ba4", "date": "10 Jul Sun", "href": "https://www.trueclassbooking.com.tw/member/popup/class-info.aspx?tcl_id=1076601", "name": "Hatha Yoga \u54c8\u9054\u745c\u73c8", "teacher": "YaYa", "time": "10:30 - 11:30 AM"}, {"room": "\u6566\u5357 4 \u6559\u5ba4", "date": "10 Jul Sun", "href": "https://www.trueclassbooking.com.tw/member/popup/class-info.aspx?tcl_id=1076602", "name": "\u76ae\u62c9\u63d0\u65af\u80fd\u91cf\u68d2", "teacher": "Joyce", "time": "04:30 - 05:30 PM"}, {"room": "\u6566\u5357 6 \u6559\u5ba4", "date": "04 Jul Mon", "href": "https://www.trueclassbooking.com.tw/member/popup/class-info.aspx?tcl_id=1076603", "name": "Mysore", "teacher": "Simon Chang", "time": "06:30 - 09:00 AM"}, {"room": "\u6566\u5357 6 \u6559\u5ba4", "date": "04 Jul Mon", "href": "https://www.trueclassbooking.com.tw/member/popup/class-info.aspx?tcl_id=1076604", "name": "Gentle Yoga \u548c\u7de9\u745c\u73c8", "teacher": "Ellen", "time": "11:00 - 12:00 PM"}, {"room": "\u6566\u5357 6 \u6559\u5ba4", "date": "04 Jul Mon", "href": "https://www.trueclassbooking.com.tw/member/popup/class-info.aspx?tcl_id=1076605", "name": "Hatha Basic \u54c8\u9054\u57fa\u790e", "teacher": "Jamie", "time": "12:30 - 01:30 PM"}, {"room": "\u6566\u5357 6 \u6559\u5ba4", "date": "04 Jul Mon", "href": "https://www.trueclassbooking.com.tw/member/popup/class-info.aspx?tcl_id=1076606", "name": "Vinyasa Intro. \u6d41\u66a2\u745c\u73c8\u5165\u9580", "teacher": "Ethan Lee", "time": "03:00 - 04:00 PM"}, {"room": "\u6566\u5357 6 \u6559\u5ba4", "date": "04 Jul Mon", "href": "https://www.trueclassbooking.com.tw/member/popup/class-info.aspx?tcl_id=1076607", "name": "\u6838\u5fc3\u7403\u8a13\u7df4", "teacher": "\u5433\u67cf\u6a35", "time": "07:00 - 08:00 PM"}, {"room": "\u6566\u5357 6 \u6559\u5ba4", "date": "04 Jul Mon", "href": "https://www.trueclassbooking.com.tw/member/popup/class-info.aspx?tcl_id=1076608", "name": "Myofascial Release \u808c\u7b4b\u819c\u6309\u6469", "teacher": "\u5433\u67cf\u6a35", "time": "08:15 - 09:15 PM"}, {"room": "\u6566\u5357 6 \u6559\u5ba4", "date": "05 Jul Tue", "href": "https://www.trueclassbooking.com.tw/member/popup/class-info.aspx?tcl_id=1076609", "name": "Mysore", "teacher": "Simon Chang", "time": "06:30 - 09:00 AM"}, {"room": "\u6566\u5357 6 \u6559\u5ba4", "date": "05 Jul Tue", "href": "https://www.trueclassbooking.com.tw/member/popup/class-info.aspx?tcl_id=1076610", "name": "Gentle Yoga \u548c\u7de9\u745c\u73c8", "teacher": "Tumai", "time": "10:30 - 11:30 AM"}, {"room": "\u6566\u5357 6 \u6559\u5ba4", "date": "05 Jul Tue", "href": "https://www.trueclassbooking.com.tw/member/popup/class-info.aspx?tcl_id=1076577", "name": "Deep Stretch \u6df1\u5ea6\u4f38\u5c55", "teacher": "Fly H.", "time": "12:30 - 01:30 PM"}, {"room": "\u6566\u5357 6 \u6559\u5ba4", "date": "05 Jul Tue", "href": "https://www.trueclassbooking.com.tw/member/popup/class-info.aspx?tcl_id=1076611", "name": "Hatha Yoga \u54c8\u9054\u745c\u73c8", "teacher": "Sophie Chan", "time": "02:15 - 03:15 PM"}, {"room": "\u6566\u5357 6 \u6559\u5ba4", "date": "05 Jul Tue", "href": "https://www.trueclassbooking.com.tw/member/popup/class-info.aspx?tcl_id=1076612", "name": "Yin Yoga \u9670\u745c\u73c8", "teacher": "Ellen", "time": "04:30 - 05:30 PM"}, {"room": "\u6566\u5357 6 \u6559\u5ba4", "date": "05 Jul Tue", "href": "https://www.trueclassbooking.com.tw/member/popup/class-info.aspx?tcl_id=1076613", "name": "Gokul Yoga", "teacher": "Andy Tenpa", "time": "07:00 - 08:00 PM"}, {"room": "\u6566\u5357 6 \u6559\u5ba4", "date": "06 Jul Wed", "href": "https://www.trueclassbooking.com.tw/member/popup/class-info.aspx?tcl_id=1076684", "name": "Mysore", "teacher": "Simon Chang", "time": "06:30 - 09:00 AM"}, {"room": "\u6566\u5357 6 \u6559\u5ba4", "date": "06 Jul Wed", "href": "https://www.trueclassbooking.com.tw/member/popup/class-info.aspx?tcl_id=1076614", "name": "Vinyasa Yoga \u6d41\u66a2\u745c\u73c8", "teacher": "William L.", "time": "11:00 - 12:00 PM"}, {"room": "\u6566\u5357 6 \u6559\u5ba4", "date": "06 Jul Wed", "href": "https://www.trueclassbooking.com.tw/member/popup/class-info.aspx?tcl_id=1076615", "name": "Aerial Yoga Basic \u7a7a\u4e2d\u745c\u73c8\u57fa\u790e", "teacher": "Joe", "time": "12:45 - 02:00 PM"}, {"room": "\u6566\u5357 6 \u6559\u5ba4", "date": "06 Jul Wed", "href": "https://www.trueclassbooking.com.tw/member/popup/class-info.aspx?tcl_id=1076617", "name": "Gentle Yoga \u548c\u7de9\u745c\u73c8", "teacher": "Priya", "time": "04:30 - 05:30 PM"}, {"room": "\u6566\u5357 6 \u6559\u5ba4", "date": "06 Jul Wed", "href": "https://www.trueclassbooking.com.tw/member/popup/class-info.aspx?tcl_id=1076618", "name": "Vinyasa Yoga2 \u6d41\u66a2\u745c\u73c8 2", "teacher": "Fly H.", "time": "07:15 - 08:45 PM"}, {"room": "\u6566\u5357 6 \u6559\u5ba4", "date": "07 Jul Thu", "href": "https://www.trueclassbooking.com.tw/member/popup/class-info.aspx?tcl_id=1076619", "name": "Mysore", "teacher": "Simon Chang", "time": "06:30 - 09:00 AM"}, {"room": "\u6566\u5357 6 \u6559\u5ba4", "date": "07 Jul Thu", "href": "https://www.trueclassbooking.com.tw/member/popup/class-info.aspx?tcl_id=1076620", "name": "Myofascial Release \u808c\u7b4b\u819c\u6309\u6469", "teacher": "\u5433\u67cf\u6a35", "time": "12:30 - 01:30 PM"}, {"room": "\u6566\u5357 6 \u6559\u5ba4", "date": "07 Jul Thu", "href": "https://www.trueclassbooking.com.tw/member/popup/class-info.aspx?tcl_id=1076621", "name": "Yin Yoga \u9670\u745c\u73c8", "teacher": "Ellen", "time": "07:00 - 08:00 PM"}, {"room": "\u6566\u5357 6 \u6559\u5ba4", "date": "07 Jul Thu", "href": "https://www.trueclassbooking.com.tw/member/popup/class-info.aspx?tcl_id=1076622", "name": "Hatha Yoga \u54c8\u9054\u745c\u73c8", "teacher": "Ellen", "time": "08:30 - 09:30 PM"}, {"room": "\u6566\u5357 6 \u6559\u5ba4", "date": "08 Jul Fri", "href": "https://www.trueclassbooking.com.tw/member/popup/class-info.aspx?tcl_id=1076623", "name": "Mysore", "teacher": "Simon Chang", "time": "06:30 - 09:00 AM"}, {"room": "\u6566\u5357 6 \u6559\u5ba4", "date": "08 Jul Fri", "href": "https://www.trueclassbooking.com.tw/member/popup/class-info.aspx?tcl_id=1076624", "name": "Healing Yoga \u7642\u7652\u745c\u73c8", "teacher": "Tumai", "time": "11:00 - 12:00 PM"}, {"room": "\u6566\u5357 6 \u6559\u5ba4", "date": "08 Jul Fri", "href": "https://www.trueclassbooking.com.tw/member/popup/class-info.aspx?tcl_id=1076625", "name": "Yoga Tone 2", "teacher": "Una", "time": "02:00 - 03:00 PM"}, {"room": "\u6566\u5357 6 \u6559\u5ba4", "date": "08 Jul Fri", "href": "https://www.trueclassbooking.com.tw/member/popup/class-info.aspx?tcl_id=1076626", "name": "Wall Yoga \u7246\u745c\u73c8", "teacher": "Moorthi", "time": "05:45 - 06:45 PM"}, {"room": "\u6566\u5357 6 \u6559\u5ba4", "date": "08 Jul Fri", "href": "https://www.trueclassbooking.com.tw/member/popup/class-info.aspx?tcl_id=1076627", "name": "Ashtanga Intro. \u963f\u65af\u5766\u52a0\u745c\u73c8\u5165\u9580", "teacher": "Simon Chang", "time": "07:15 - 08:15 PM"}, {"room": "\u6566\u5357 6 \u6559\u5ba4", "date": "08 Jul Fri", "href": "https://www.trueclassbooking.com.tw/member/popup/class-info.aspx?tcl_id=1076628", "name": "Gentle Yoga \u548c\u7de9\u745c\u73c8", "teacher": "Pearl", "time": "08:45 - 09:45 PM"}, {"room": "\u6566\u5357 6 \u6559\u5ba4", "date": "09 Jul Sat", "href": "https://www.trueclassbooking.com.tw/member/popup/class-info.aspx?tcl_id=1076629", "name": "Ashtanga 2 & Conference", "teacher": "Simon Chang", "time": "08:30 - 10:30 AM"}, {"room": "\u6566\u5357 6 \u6559\u5ba4", "date": "09 Jul Sat", "href": "https://www.trueclassbooking.com.tw/member/popup/class-info.aspx?tcl_id=1076597", "name": "Flow Yoga \u52d5\u745c\u73c8", "teacher": "Moorthi", "time": "11:00 - 12:00 PM"}, {"room": "\u6566\u5357 6 \u6559\u5ba4", "date": "09 Jul Sat", "href": "https://www.trueclassbooking.com.tw/member/popup/class-info.aspx?tcl_id=1076598", "name": "Deep Stretch \u6df1\u5ea6\u4f38\u5c55", "teacher": "Fly H.", "time": "02:00 - 03:00 PM"}, {"room": "\u6566\u5357 6 \u6559\u5ba4", "date": "09 Jul Sat", "href": "https://www.trueclassbooking.com.tw/member/popup/class-info.aspx?tcl_id=1076631", "name": "Yin Yoga \u9670\u745c\u73c8", "teacher": "Abel", "time": "04:30 - 05:30 PM"}, {"room": "\u6566\u5357 6 \u6559\u5ba4", "date": "09 Jul Sat", "href": "https://www.trueclassbooking.com.tw/member/popup/class-info.aspx?tcl_id=1076632", "name": "Hatha Yoga \u54c8\u9054\u745c\u73c8", "teacher": "Coco Wang", "time": "06:15 - 07:15 PM"}, {"room": "\u6566\u5357 6 \u6559\u5ba4", "date": "10 Jul Sun", "href": "https://www.trueclassbooking.com.tw/member/popup/class-info.aspx?tcl_id=1076633", "name": "Gentle Yoga \u548c\u7de9\u745c\u73c8", "teacher": "Una", "time": "10:15 - 11:15 AM"}, {"room": "\u6566\u5357 6 \u6559\u5ba4", "date": "10 Jul Sun", "href": "https://www.trueclassbooking.com.tw/member/popup/class-info.aspx?tcl_id=1076634", "name": "Universal Intro. \u5bf0\u5b87\u745c\u73c8\u5165\u9580", "teacher": "YaYa", "time": "12:30 - 01:30 PM"}, {"room": "\u6566\u5357 6 \u6559\u5ba4", "date": "10 Jul Sun", "href": "https://www.trueclassbooking.com.tw/member/popup/class-info.aspx?tcl_id=1076635", "name": "Yin Yoga \u9670\u745c\u73c8", "teacher": "YaYa", "time": "03:45 - 04:45 PM"}, {"room": "\u6566\u5357 7 \u6559\u5ba4", "date": "04 Jul Mon", "href": "https://www.trueclassbooking.com.tw/member/popup/class-info.aspx?tcl_id=1076636", "name": "Yoga Tone", "teacher": "Una", "time": "09:00 - 10:00 AM"}, {"room": "\u6566\u5357 7 \u6559\u5ba4", "date": "04 Jul Mon", "href": "https://www.trueclassbooking.com.tw/member/popup/class-info.aspx?tcl_id=1076637", "name": "*YE \u5718\u9ad4\u5c0f\u73ed*", "teacher": "Una", "time": "12:00 - 01:00 PM"}, {"room": "\u6566\u5357 7 \u6559\u5ba4", "date": "04 Jul Mon", "href": "https://www.trueclassbooking.com.tw/member/popup/class-info.aspx?tcl_id=1076638", "name": "Yoga Stretch \u4f38\u5c55\u745c\u73c8", "teacher": "Claire", "time": "03:30 - 04:30 PM"}, {"room": "\u6566\u5357 7 \u6559\u5ba4", "date": "04 Jul Mon", "href": "https://www.trueclassbooking.com.tw/member/popup/class-info.aspx?tcl_id=1076639", "name": "Iyengar Yoga (Wall Rope) - \u827e\u63da\u683c\u745c\u73c8 \u58c1\u7e69", "teacher": "Yvette", "time": "06:00 - 07:00 PM"}, {"room": "\u6566\u5357 7 \u6559\u5ba4", "date": "04 Jul Mon", "href": "https://www.trueclassbooking.com.tw/member/popup/class-info.aspx?tcl_id=1076640", "name": "Hatha Yoga \u54c8\u9054\u6b63\u4f4d", "teacher": "Yvette", "time": "07:30 - 08:30 PM"}, {"room": "\u6566\u5357 7 \u6559\u5ba4", "date": "05 Jul Tue", "href": "https://www.trueclassbooking.com.tw/member/popup/class-info.aspx?tcl_id=1076668", "name": "Hatha Yoga \u54c8\u9054\u745c\u73c8", "teacher": "Tumai", "time": "09:00 - 10:00 AM"}, {"room": "\u6566\u5357 7 \u6559\u5ba4", "date": "05 Jul Tue", "href": "https://www.trueclassbooking.com.tw/member/popup/class-info.aspx?tcl_id=1076641", "name": "Vinyasa Yoga \u6d41\u66a2\u745c\u73c8", "teacher": "Fly H.", "time": "11:15 - 12:15 PM"}, {"room": "\u6566\u5357 7 \u6559\u5ba4", "date": "05 Jul Tue", "href": "https://www.trueclassbooking.com.tw/member/popup/class-info.aspx?tcl_id=1076578", "name": "Gentle Yoga \u548c\u7de9\u745c\u73c8", "teacher": "Una", "time": "04:00 - 05:00 PM"}, {"room": "\u6566\u5357 7 \u6559\u5ba4", "date": "05 Jul Tue", "href": "https://www.trueclassbooking.com.tw/member/popup/class-info.aspx?tcl_id=1076579", "name": "Hatha Yoga \u54c8\u9054\u745c\u73c8", "teacher": "Yvette", "time": "06:15 - 07:15 PM"}, {"room": "\u6566\u5357 7 \u6559\u5ba4", "date": "05 Jul Tue", "href": "https://www.trueclassbooking.com.tw/member/popup/class-info.aspx?tcl_id=1076580", "name": "Gentle Yoga \u548c\u7de9\u745c\u73c8", "teacher": "Andy Tenpa", "time": "08:30 - 09:30 PM"}, {"room": "\u6566\u5357 7 \u6559\u5ba4", "date": "06 Jul Wed", "href": "https://www.trueclassbooking.com.tw/member/popup/class-info.aspx?tcl_id=1076644", "name": "Hatha Yoga \u54c8\u9054\u745c\u73c8", "teacher": "Sophie Chan", "time": "10:15 - 11:15 AM"}, {"room": "\u6566\u5357 7 \u6559\u5ba4", "date": "06 Jul Wed", "href": "https://www.trueclassbooking.com.tw/member/popup/class-info.aspx?tcl_id=1076645", "name": "Yoga Stretch \u4f38\u5c55\u745c\u73c8", "teacher": "Sophie Chan", "time": "12:15 - 01:15 PM"}, {"room": "\u6566\u5357 7 \u6559\u5ba4", "date": "06 Jul Wed", "href": "https://www.trueclassbooking.com.tw/member/popup/class-info.aspx?tcl_id=1076583", "name": "Hatha Yoga \u54c8\u9054\u745c\u73c8", "teacher": "Priya", "time": "03:00 - 04:00 PM"}, {"room": "\u6566\u5357 7 \u6559\u5ba4", "date": "06 Jul Wed", "href": "https://www.trueclassbooking.com.tw/member/popup/class-info.aspx?tcl_id=1076647", "name": "Hatha Yoga \u54c8\u9054\u6b63\u4f4d", "teacher": "Yvette", "time": "07:30 - 08:30 PM"}, {"room": "\u6566\u5357 7 \u6559\u5ba4", "date": "07 Jul Thu", "href": "https://www.trueclassbooking.com.tw/member/popup/class-info.aspx?tcl_id=1076648", "name": "Iyengar Basic \u827e\u63da\u683c\u57fa\u790e", "teacher": "Yvette", "time": "10:30 - 11:30 AM"}, {"room": "\u6566\u5357 7 \u6559\u5ba4", "date": "07 Jul Thu", "href": "https://www.trueclassbooking.com.tw/member/popup/class-info.aspx?tcl_id=1076649", "name": "Hatha Yoga \u54c8\u9054\u745c\u73c8", "teacher": "Coco Wang", "time": "12:15 - 01:15 PM"}, {"room": "\u6566\u5357 7 \u6559\u5ba4", "date": "07 Jul Thu", "href": "https://www.trueclassbooking.com.tw/member/popup/class-info.aspx?tcl_id=1076650", "name": "Vinyasa Yoga \u6d41\u66a2\u745c\u73c8", "teacher": "Fly H.", "time": "06:45 - 07:45 PM"}, {"room": "\u6566\u5357 7 \u6559\u5ba4", "date": "07 Jul Thu", "href": "https://www.trueclassbooking.com.tw/member/popup/class-info.aspx?tcl_id=1076651", "name": "Chair Stretch \u6905\u5b50\u4f38\u5c55", "teacher": "Fly H.", "time": "08:15 - 09:15 PM"}, {"room": "\u6566\u5357 7 \u6559\u5ba4", "date": "08 Jul Fri", "href": "https://www.trueclassbooking.com.tw/member/popup/class-info.aspx?tcl_id=1076652", "name": "Iyengar Yoga (Wall Rope) - \u827e\u63da\u683c\u745c\u73c8 \u58c1\u7e69", "teacher": "Yvette", "time": "09:00 - 10:00 AM"}, {"room": "\u6566\u5357 7 \u6559\u5ba4", "date": "08 Jul Fri", "href": "https://www.trueclassbooking.com.tw/member/popup/class-info.aspx?tcl_id=1076653", "name": "Yoga Stretch \u4f38\u5c55\u745c\u73c8", "teacher": "Soni", "time": "10:30 - 11:30 AM"}, {"room": "\u6566\u5357 7 \u6559\u5ba4", "date": "08 Jul Fri", "href": "https://www.trueclassbooking.com.tw/member/popup/class-info.aspx?tcl_id=1076654", "name": "Vinyasa Yoga \u6d41\u66a2\u745c\u73c8", "teacher": "Soni", "time": "12:15 - 01:15 PM"}, {"room": "\u6566\u5357 7 \u6559\u5ba4", "date": "08 Jul Fri", "href": "https://www.trueclassbooking.com.tw/member/popup/class-info.aspx?tcl_id=1076655", "name": "Hatha Yoga \u54c8\u9054\u745c\u73c8", "teacher": "Coco Wang", "time": "02:30 - 03:30 PM"}, {"room": "\u6566\u5357 7 \u6559\u5ba4", "date": "08 Jul Fri", "href": "https://www.trueclassbooking.com.tw/member/popup/class-info.aspx?tcl_id=1076656", "name": "Vinyasa Intro \u6d41\u66a2\u745c\u73c8\u5165\u9580", "teacher": "Coco Wang", "time": "04:00 - 05:00 PM"}, {"room": "\u6566\u5357 7 \u6559\u5ba4", "date": "08 Jul Fri", "href": "https://www.trueclassbooking.com.tw/member/popup/class-info.aspx?tcl_id=1076657", "name": "Hatha Yoga \u54c8\u9054\u745c\u73c8 1", "teacher": "Priya", "time": "06:15 - 07:15 PM"}, {"room": "\u6566\u5357 7 \u6559\u5ba4", "date": "08 Jul Fri", "href": "https://www.trueclassbooking.com.tw/member/popup/class-info.aspx?tcl_id=1076658", "name": "Yin Yoga \u9670\u745c\u73c8", "teacher": "Priya", "time": "07:45 - 08:45 PM"}, {"room": "\u6566\u5357 7 \u6559\u5ba4", "date": "09 Jul Sat", "href": "https://www.trueclassbooking.com.tw/member/popup/class-info.aspx?tcl_id=1076659", "name": "Yin Yoga \u9670\u745c\u73c8", "teacher": "Moorthi", "time": "09:30 - 10:30 AM"}, {"room": "\u6566\u5357 7 \u6559\u5ba4", "date": "09 Jul Sat", "href": "https://www.trueclassbooking.com.tw/member/popup/class-info.aspx?tcl_id=1076630", "name": "Core Yoga \u6838\u5fc3\u745c\u73c8", "teacher": "Fly H.", "time": "12:30 - 01:30 PM"}, {"room": "\u6566\u5357 7 \u6559\u5ba4", "date": "09 Jul Sat", "href": "https://www.trueclassbooking.com.tw/member/popup/class-info.aspx?tcl_id=1076661", "name": "Hatha Yoga \u54c8\u9054\u745c\u73c8", "teacher": "Abel", "time": "03:00 - 04:00 PM"}, {"room": "\u6566\u5357 7 \u6559\u5ba4", "date": "10 Jul Sun", "href": "https://www.trueclassbooking.com.tw/member/popup/class-info.aspx?tcl_id=1076662", "name": "Vinyasa Yoga \u6d41\u66a2\u745c\u73c8", "teacher": "Una", "time": "09:00 - 10:00 AM"}, {"room": "\u6566\u5357 7 \u6559\u5ba4", "date": "10 Jul Sun", "href": "https://www.trueclassbooking.com.tw/member/popup/class-info.aspx?tcl_id=1076663", "name": "Universal Yoga \u5bf0\u5b87\u745c\u73c8", "teacher": "YaYa", "time": "02:00 - 03:30 PM"}, {"room": "\u6566\u5357 7 \u6559\u5ba4", "date": "10 Jul Sun", "href": "https://www.trueclassbooking.com.tw/member/popup/class-info.aspx?tcl_id=1076664", "name": "Vinyasa Intro \u6d41\u66a2\u745c\u73c8\u5165\u9580", "teacher": "Coco Wang", "time": "05:30 - 06:30 PM"}]