[{"room": "\u6566\u5357 4 \u6559\u5ba4", "date": "26 Apr Mon", "href": "https://www.trueclassbooking.com.tw/member/popup/class-info.aspx?tcl_id=814756", "name": "Hatha Yoga \u54c8\u9054\u745c\u73c8", "teacher": "Una", "time": "07:15 - 08:15 AM"}, {"room": "\u6566\u5357 4 \u6559\u5ba4", "date": "26 Apr Mon", "href": "https://www.trueclassbooking.com.tw/member/popup/class-info.aspx?tcl_id=814757", "name": "Vinyasa Yoga \u6d41\u66a2\u745c\u73c8", "teacher": "Una", "time": "10:30 - 11:30 AM"}, {"room": "\u6566\u5357 4 \u6559\u5ba4", "date": "26 Apr Mon", "href": "https://www.trueclassbooking.com.tw/member/popup/class-info.aspx?tcl_id=814758", "name": "\u6efe\u7b52\u7d9c\u5408\u8a13\u7df4", "teacher": "Jamie", "time": "02:00 - 03:00 PM"}, {"room": "\u6566\u5357 4 \u6559\u5ba4", "date": "26 Apr Mon", "href": "https://www.trueclassbooking.com.tw/member/popup/class-info.aspx?tcl_id=814759", "name": "Yoga Wheel \u745c\u73c8\u8f2a", "teacher": "Coco Wang", "time": "03:30 - 04:30 PM"}, {"room": "\u6566\u5357 4 \u6559\u5ba4", "date": "26 Apr Mon", "href": "https://www.trueclassbooking.com.tw/member/popup/class-info.aspx?tcl_id=814760", "name": "Hatha Yoga \u54c8\u9054\u745c\u73c8", "teacher": "Fly H.", "time": "06:15 - 07:15 PM"}, {"room": "\u6566\u5357 4 \u6559\u5ba4", "date": "26 Apr Mon", "href": "https://www.trueclassbooking.com.tw/member/popup/class-info.aspx?tcl_id=814761", "name": "Vinyasa Yoga \u6d41\u66a2\u745c\u73c8", "teacher": "Fly H.", "time": "07:30 - 08:30 PM"}, {"room": "\u6566\u5357 4 \u6559\u5ba4", "date": "27 Apr Tue", "href": "https://www.trueclassbooking.com.tw/member/popup/class-info.aspx?tcl_id=814762", "name": "Vinyasa Intro \u6d41\u66a2\u745c\u73c8\u5165\u9580", "teacher": "William L.", "time": "07:15 - 08:15 AM"}, {"room": "\u6566\u5357 4 \u6559\u5ba4", "date": "27 Apr Tue", "href": "https://www.trueclassbooking.com.tw/member/popup/class-info.aspx?tcl_id=814763", "name": "Yoga Wheel \u745c\u73c8\u8f2a", "teacher": "Simon Chang", "time": "09:30 - 10:30 AM"}, {"room": "\u6566\u5357 4 \u6559\u5ba4", "date": "27 Apr Tue", "href": "https://www.trueclassbooking.com.tw/member/popup/class-info.aspx?tcl_id=814764", "name": "Vinyasa Yoga \u6d41\u66a2\u745c\u73c8", "teacher": "Minthia", "time": "12:45 - 02:00 PM"}, {"room": "\u6566\u5357 4 \u6559\u5ba4", "date": "27 Apr Tue", "href": "https://www.trueclassbooking.com.tw/member/popup/class-info.aspx?tcl_id=814765", "name": "Hatha Yoga \u54c8\u9054\u745c\u73c8 1", "teacher": "Mei Wang", "time": "03:15 - 04:15 PM"}, {"room": "\u6566\u5357 4 \u6559\u5ba4", "date": "27 Apr Tue", "href": "https://www.trueclassbooking.com.tw/member/popup/class-info.aspx?tcl_id=814766", "name": "Vinyasa Yoga \u6d41\u66a2\u745c\u73c8", "teacher": "Andrew B.", "time": "05:30 - 06:30 PM"}, {"room": "\u6566\u5357 4 \u6559\u5ba4", "date": "27 Apr Tue", "href": "https://www.trueclassbooking.com.tw/member/popup/class-info.aspx?tcl_id=814767", "name": "Vinyasa Yoga \u6d41\u66a2\u745c\u73c8", "teacher": "Una", "time": "07:15 - 08:30 PM"}, {"room": "\u6566\u5357 4 \u6559\u5ba4", "date": "28 Apr Wed", "href": "https://www.trueclassbooking.com.tw/member/popup/class-info.aspx?tcl_id=814768", "name": "Hatha Yoga \u54c8\u9054\u745c\u73c8", "teacher": "Coco Wang", "time": "07:15 - 08:15 AM"}, {"room": "\u6566\u5357 4 \u6559\u5ba4", "date": "28 Apr Wed", "href": "https://www.trueclassbooking.com.tw/member/popup/class-info.aspx?tcl_id=814769", "name": "\u592a\u6975\u745c\u73c8\u80fd\u91cf\u68d2", "teacher": "Joyce", "time": "10:30 - 11:30 AM"}, {"room": "\u6566\u5357 4 \u6559\u5ba4", "date": "28 Apr Wed", "href": "https://www.trueclassbooking.com.tw/member/popup/class-info.aspx?tcl_id=814770", "name": "Vinyasa Yoga \u6d41\u66a2\u745c\u73c8", "teacher": "Abel", "time": "12:45 - 01:45 PM"}, {"room": "\u6566\u5357 4 \u6559\u5ba4", "date": "28 Apr Wed", "href": "https://www.trueclassbooking.com.tw/member/popup/class-info.aspx?tcl_id=814771", "name": "Core Yoga \u6838\u5fc3\u745c\u73c8", "teacher": "Abel", "time": "02:30 - 03:30 PM"}, {"room": "\u6566\u5357 4 \u6559\u5ba4", "date": "28 Apr Wed", "href": "https://www.trueclassbooking.com.tw/member/popup/class-info.aspx?tcl_id=814772", "name": "Hatha Yoga \u54c8\u9054\u745c\u73c8", "teacher": "Abel", "time": "03:45 - 04:45 PM"}, {"room": "\u6566\u5357 4 \u6559\u5ba4", "date": "28 Apr Wed", "href": "https://www.trueclassbooking.com.tw/member/popup/class-info.aspx?tcl_id=814773", "name": "\u54c8\u9054\u6b63\u4f4d", "teacher": "Yvette", "time": "05:45 - 06:45 PM"}, {"room": "\u6566\u5357 4 \u6559\u5ba4", "date": "28 Apr Wed", "href": "https://www.trueclassbooking.com.tw/member/popup/class-info.aspx?tcl_id=814774", "name": "Vinyasa Yoga2 \u6d41\u66a2\u745c\u73c8 2", "teacher": "Fly H.", "time": "07:15 - 08:45 PM"}, {"room": "\u6566\u5357 4 \u6559\u5ba4", "date": "28 Apr Wed", "href": "https://www.trueclassbooking.com.tw/member/popup/class-info.aspx?tcl_id=814775", "name": "\u6df1\u5ea6\u4f38\u5c55", "teacher": "Fly H.", "time": "09:00 - 10:15 PM"}, {"room": "\u6566\u5357 4 \u6559\u5ba4", "date": "29 Apr Thu", "href": "https://www.trueclassbooking.com.tw/member/popup/class-info.aspx?tcl_id=814776", "name": "\u6efe\u7b52\u7d9c\u5408\u8a13\u7df4", "teacher": "Jamie", "time": "09:00 - 10:00 AM"}, {"room": "\u6566\u5357 4 \u6559\u5ba4", "date": "29 Apr Thu", "href": "https://www.trueclassbooking.com.tw/member/popup/class-info.aspx?tcl_id=814777", "name": "Vinyasa Yoga \u6d41\u66a2\u745c\u73c8", "teacher": "Coco Wang", "time": "12:45 - 01:45 PM"}, {"room": "\u6566\u5357 4 \u6559\u5ba4", "date": "29 Apr Thu", "href": "https://www.trueclassbooking.com.tw/member/popup/class-info.aspx?tcl_id=814778", "name": "Gentle Yoga \u548c\u7de9\u745c\u73c8", "teacher": "Simon Chang", "time": "04:30 - 05:30 PM"}, {"room": "\u6566\u5357 4 \u6559\u5ba4", "date": "29 Apr Thu", "href": "https://www.trueclassbooking.com.tw/member/popup/class-info.aspx?tcl_id=814779", "name": "Vinyasa Yoga \u6d41\u66a2\u745c\u73c8", "teacher": "Andy Tenpa", "time": "06:15 - 07:15 PM"}, {"room": "\u6566\u5357 4 \u6559\u5ba4", "date": "29 Apr Thu", "href": "https://www.trueclassbooking.com.tw/member/popup/class-info.aspx?tcl_id=814780", "name": "Hatha Yoga \u54c8\u9054\u745c\u73c8", "teacher": "Andy Tenpa", "time": "07:30 - 08:30 PM"}, {"room": "\u6566\u5357 4 \u6559\u5ba4", "date": "30 Apr Fri", "href": "https://www.trueclassbooking.com.tw/member/popup/class-info.aspx?tcl_id=814913", "name": "*YE \u5718\u9ad4\u5c0f\u73ed*", "teacher": "Carolyn", "time": "10:00 - 12:00 PM"}, {"room": "\u6566\u5357 4 \u6559\u5ba4", "date": "30 Apr Fri", "href": "https://www.trueclassbooking.com.tw/member/popup/class-info.aspx?tcl_id=814782", "name": "Vinyasa Yoga \u6d41\u66a2\u745c\u73c8", "teacher": "Coco Wang", "time": "12:45 - 01:45 PM"}, {"room": "\u6566\u5357 4 \u6559\u5ba4", "date": "30 Apr Fri", "href": "https://www.trueclassbooking.com.tw/member/popup/class-info.aspx?tcl_id=814783", "name": "Yoga Wheel \u745c\u73c8\u8f2a", "teacher": "Una", "time": "03:15 - 04:15 PM"}, {"room": "\u6566\u5357 4 \u6559\u5ba4", "date": "30 Apr Fri", "href": "https://www.trueclassbooking.com.tw/member/popup/class-info.aspx?tcl_id=814784", "name": "Gentle Yoga \u548c\u7de9\u745c\u73c8", "teacher": "Ellen", "time": "04:30 - 05:30 PM"}, {"room": "\u6566\u5357 4 \u6559\u5ba4", "date": "30 Apr Fri", "href": "https://www.trueclassbooking.com.tw/member/popup/class-info.aspx?tcl_id=814785", "name": "Ashtanga Intro. \u963f\u65af\u5766\u52a0\u745c\u73c8\u5165\u9580", "teacher": "Simon Chang", "time": "06:45 - 08:00 PM"}, {"room": "\u6566\u5357 4 \u6559\u5ba4", "date": "30 Apr Fri", "href": "https://www.trueclassbooking.com.tw/member/popup/class-info.aspx?tcl_id=814786", "name": "Hatha Yoga \u54c8\u9054\u745c\u73c8", "teacher": "Andy Tenpa", "time": "08:15 - 09:15 PM"}, {"room": "\u6566\u5357 4 \u6559\u5ba4", "date": "01 May Sat", "href": "https://www.trueclassbooking.com.tw/member/popup/class-info.aspx?tcl_id=814788", "name": "Hatha Yoga \u54c8\u9054\u745c\u73c8", "teacher": "Simon Chang", "time": "12:30 - 01:45 PM"}, {"room": "\u6566\u5357 4 \u6559\u5ba4", "date": "01 May Sat", "href": "https://www.trueclassbooking.com.tw/member/popup/class-info.aspx?tcl_id=814789", "name": "Hatha Yoga \u54c8\u9054\u745c\u73c8", "teacher": "Wei Lee", "time": "02:30 - 03:30 PM"}, {"room": "\u6566\u5357 4 \u6559\u5ba4", "date": "01 May Sat", "href": "https://www.trueclassbooking.com.tw/member/popup/class-info.aspx?tcl_id=814790", "name": "Vinyasa Yoga \u6d41\u66a2\u745c\u73c8", "teacher": "Coco Wang", "time": "05:00 - 06:00 PM"}, {"room": "\u6566\u5357 4 \u6559\u5ba4", "date": "02 May Sun", "href": "https://www.trueclassbooking.com.tw/member/popup/class-info.aspx?tcl_id=814791", "name": "Vinyasa Yoga \u6d41\u66a2\u745c\u73c8 1", "teacher": "Una", "time": "09:00 - 10:00 AM"}, {"room": "\u6566\u5357 4 \u6559\u5ba4", "date": "02 May Sun", "href": "https://www.trueclassbooking.com.tw/member/popup/class-info.aspx?tcl_id=814792", "name": "Rocket Yoga \u706b\u7bad\u745c\u73c8", "teacher": "Una", "time": "11:30 - 01:00 PM"}, {"room": "\u6566\u5357 6 \u6559\u5ba4", "date": "26 Apr Mon", "href": "https://www.trueclassbooking.com.tw/member/popup/class-info.aspx?tcl_id=814794", "name": "Mysore", "teacher": "Simon Chang", "time": "06:30 - 09:00 AM"}, {"room": "\u6566\u5357 6 \u6559\u5ba4", "date": "26 Apr Mon", "href": "https://www.trueclassbooking.com.tw/member/popup/class-info.aspx?tcl_id=814795", "name": "Yin Yoga \u9670\u745c\u73c8", "teacher": "Ellen", "time": "09:30 - 10:30 AM"}, {"room": "\u6566\u5357 6 \u6559\u5ba4", "date": "26 Apr Mon", "href": "https://www.trueclassbooking.com.tw/member/popup/class-info.aspx?tcl_id=814796", "name": "Hatha Basic \u54c8\u9054\u57fa\u790e", "teacher": "Jamie", "time": "12:30 - 01:30 PM"}, {"room": "\u6566\u5357 6 \u6559\u5ba4", "date": "26 Apr Mon", "href": "https://www.trueclassbooking.com.tw/member/popup/class-info.aspx?tcl_id=814797", "name": "Mysore", "teacher": "Simon Chang", "time": "02:30 - 04:00 PM"}, {"room": "\u6566\u5357 6 \u6559\u5ba4", "date": "26 Apr Mon", "href": "https://www.trueclassbooking.com.tw/member/popup/class-info.aspx?tcl_id=814798", "name": "Vinyasa Yoga \u6d41\u66a2\u745c\u73c8", "teacher": "Tumai", "time": "05:30 - 06:30 PM"}, {"room": "\u6566\u5357 6 \u6559\u5ba4", "date": "26 Apr Mon", "href": "https://www.trueclassbooking.com.tw/member/popup/class-info.aspx?tcl_id=814799", "name": "\u6838\u5fc3\u7403\u8a13\u7df4", "teacher": "\u5433\u67cf\u6a35", "time": "07:00 - 08:00 PM"}, {"room": "\u6566\u5357 6 \u6559\u5ba4", "date": "26 Apr Mon", "href": "https://www.trueclassbooking.com.tw/member/popup/class-info.aspx?tcl_id=814800", "name": "Myofascial Release \u808c\u7b4b\u819c\u6309\u6469", "teacher": "\u5433\u67cf\u6a35", "time": "08:15 - 09:30 PM"}, {"room": "\u6566\u5357 6 \u6559\u5ba4", "date": "27 Apr Tue", "href": "https://www.trueclassbooking.com.tw/member/popup/class-info.aspx?tcl_id=814802", "name": "Gentle Yoga \u548c\u7de9\u745c\u73c8", "teacher": "Andy Tenpa", "time": "10:30 - 11:30 AM"}, {"room": "\u6566\u5357 6 \u6559\u5ba4", "date": "27 Apr Tue", "href": "https://www.trueclassbooking.com.tw/member/popup/class-info.aspx?tcl_id=814803", "name": "\u6df1\u5ea6\u4f38\u5c55", "teacher": "Fly H.", "time": "12:30 - 01:45 PM"}, {"room": "\u6566\u5357 6 \u6559\u5ba4", "date": "27 Apr Tue", "href": "https://www.trueclassbooking.com.tw/member/popup/class-info.aspx?tcl_id=814804", "name": "Vinyasa Yoga2 \u6d41\u66a2\u745c\u73c8 2", "teacher": "Jaelyn", "time": "02:15 - 03:30 PM"}, {"room": "\u6566\u5357 6 \u6559\u5ba4", "date": "27 Apr Tue", "href": "https://www.trueclassbooking.com.tw/member/popup/class-info.aspx?tcl_id=814805", "name": "Yin Yoga \u9670\u745c\u73c8", "teacher": "Mei Wang", "time": "04:30 - 05:45 PM"}, {"room": "\u6566\u5357 6 \u6559\u5ba4", "date": "27 Apr Tue", "href": "https://www.trueclassbooking.com.tw/member/popup/class-info.aspx?tcl_id=814806", "name": "Vinyasa Intro \u6d41\u66a2\u745c\u73c8\u5165\u9580", "teacher": "Una", "time": "06:00 - 07:00 PM"}, {"room": "\u6566\u5357 6 \u6559\u5ba4", "date": "27 Apr Tue", "href": "https://www.trueclassbooking.com.tw/member/popup/class-info.aspx?tcl_id=814807", "name": "Hatha Yoga \u54c8\u9054\u745c\u73c8", "teacher": "Tumai", "time": "07:30 - 08:30 PM"}, {"room": "\u6566\u5357 6 \u6559\u5ba4", "date": "27 Apr Tue", "href": "https://www.trueclassbooking.com.tw/member/popup/class-info.aspx?tcl_id=814808", "name": "Restorative Yoga \u4fee\u5fa9\u745c\u73c8", "teacher": "Tumai", "time": "08:45 - 09:45 PM"}, {"room": "\u6566\u5357 6 \u6559\u5ba4", "date": "28 Apr Wed", "href": "https://www.trueclassbooking.com.tw/member/popup/class-info.aspx?tcl_id=814809", "name": "Mysore", "teacher": "Simon Chang", "time": "06:30 - 09:00 AM"}, {"room": "\u6566\u5357 6 \u6559\u5ba4", "date": "28 Apr Wed", "href": "https://www.trueclassbooking.com.tw/member/popup/class-info.aspx?tcl_id=814810", "name": "*YE \u5718\u9ad4\u5c0f\u73ed*", "teacher": "Una", "time": "11:00 - 02:30 PM"}, {"room": "\u6566\u5357 6 \u6559\u5ba4", "date": "28 Apr Wed", "href": "https://www.trueclassbooking.com.tw/member/popup/class-info.aspx?tcl_id=814811", "name": "Aerial Yoga Basic \u7a7a\u4e2d\u745c\u73c8\u57fa\u790e", "teacher": "Una", "time": "03:00 - 04:00 PM"}, {"room": "\u6566\u5357 6 \u6559\u5ba4", "date": "28 Apr Wed", "href": "https://www.trueclassbooking.com.tw/member/popup/class-info.aspx?tcl_id=814812", "name": "Ashtanga \u963f\u65af\u5766\u52a0 1", "teacher": "Carolyn", "time": "06:00 - 07:15 PM"}, {"room": "\u6566\u5357 6 \u6559\u5ba4", "date": "28 Apr Wed", "href": "https://www.trueclassbooking.com.tw/member/popup/class-info.aspx?tcl_id=814813", "name": "Hatha Yoga \u54c8\u9054\u745c\u73c8", "teacher": "Ethan Lee", "time": "08:15 - 09:15 PM"}, {"room": "\u6566\u5357 6 \u6559\u5ba4", "date": "29 Apr Thu", "href": "https://www.trueclassbooking.com.tw/member/popup/class-info.aspx?tcl_id=814814", "name": "Mysore", "teacher": "Simon Chang", "time": "06:30 - 09:00 AM"}, {"room": "\u6566\u5357 6 \u6559\u5ba4", "date": "29 Apr Thu", "href": "https://www.trueclassbooking.com.tw/member/popup/class-info.aspx?tcl_id=814815", "name": "Core Yoga \u6838\u5fc3\u745c\u73c8", "teacher": "Mei Wang", "time": "11:00 - 12:00 PM"}, {"room": "\u6566\u5357 6 \u6559\u5ba4", "date": "29 Apr Thu", "href": "https://www.trueclassbooking.com.tw/member/popup/class-info.aspx?tcl_id=814816", "name": "Myofascial Release \u808c\u7b4b\u819c\u6309\u6469", "teacher": "\u5433\u67cf\u6a35", "time": "12:30 - 01:45 PM"}, {"room": "\u6566\u5357 6 \u6559\u5ba4", "date": "29 Apr Thu", "href": "https://www.trueclassbooking.com.tw/member/popup/class-info.aspx?tcl_id=814817", "name": "Aerial Yoga \u7a7a\u4e2d\u745c\u73c8", "teacher": "Melissa", "time": "03:45 - 04:45 PM"}, {"room": "\u6566\u5357 6 \u6559\u5ba4", "date": "29 Apr Thu", "href": "https://www.trueclassbooking.com.tw/member/popup/class-info.aspx?tcl_id=814818", "name": "Yoga Tone", "teacher": "Una", "time": "06:00 - 07:00 PM"}, {"room": "\u6566\u5357 6 \u6559\u5ba4", "date": "29 Apr Thu", "href": "https://www.trueclassbooking.com.tw/member/popup/class-info.aspx?tcl_id=814819", "name": "Rocket Yoga \u706b\u7bad\u745c\u73c8", "teacher": "Una", "time": "07:15 - 08:45 PM"}, {"room": "\u6566\u5357 6 \u6559\u5ba4", "date": "29 Apr Thu", "href": "https://www.trueclassbooking.com.tw/member/popup/class-info.aspx?tcl_id=814820", "name": "Aerial Yoga \u7a7a\u4e2d\u745c\u73c8", "teacher": "Una", "time": "09:00 - 10:00 PM"}, {"room": "\u6566\u5357 6 \u6559\u5ba4", "date": "30 Apr Fri", "href": "https://www.trueclassbooking.com.tw/member/popup/class-info.aspx?tcl_id=814821", "name": "Mysore", "teacher": "Simon Chang", "time": "06:30 - 09:00 AM"}, {"room": "\u6566\u5357 6 \u6559\u5ba4", "date": "30 Apr Fri", "href": "https://www.trueclassbooking.com.tw/member/popup/class-info.aspx?tcl_id=814822", "name": "Hatha Yoga \u54c8\u9054\u745c\u73c8", "teacher": "Coco Wang", "time": "10:30 - 11:30 AM"}, {"room": "\u6566\u5357 6 \u6559\u5ba4", "date": "30 Apr Fri", "href": "https://www.trueclassbooking.com.tw/member/popup/class-info.aspx?tcl_id=814823", "name": "Yoga Tone 2", "teacher": "Una", "time": "02:00 - 03:00 PM"}, {"room": "\u6566\u5357 6 \u6559\u5ba4", "date": "30 Apr Fri", "href": "https://www.trueclassbooking.com.tw/member/popup/class-info.aspx?tcl_id=814824", "name": "Hatha Yoga \u54c8\u9054\u745c\u73c8", "teacher": "Andy Tenpa", "time": "04:00 - 05:00 PM"}, {"room": "\u6566\u5357 6 \u6559\u5ba4", "date": "30 Apr Fri", "href": "https://www.trueclassbooking.com.tw/member/popup/class-info.aspx?tcl_id=814825", "name": "Hatha Yoga \u54c8\u9054\u745c\u73c8", "teacher": "Priya", "time": "06:15 - 07:15 PM"}, {"room": "\u6566\u5357 6 \u6559\u5ba4", "date": "30 Apr Fri", "href": "https://www.trueclassbooking.com.tw/member/popup/class-info.aspx?tcl_id=814826", "name": "Yin Yoga \u9670\u745c\u73c8", "teacher": "Priya", "time": "07:30 - 08:45 PM"}, {"room": "\u6566\u5357 6 \u6559\u5ba4", "date": "01 May Sat", "href": "https://www.trueclassbooking.com.tw/member/popup/class-info.aspx?tcl_id=814827", "name": "Yin Yoga \u9670\u745c\u73c8", "teacher": "Moorthi", "time": "09:30 - 10:30 AM"}, {"room": "\u6566\u5357 6 \u6559\u5ba4", "date": "01 May Sat", "href": "https://www.trueclassbooking.com.tw/member/popup/class-info.aspx?tcl_id=814828", "name": "Vinyasa Yoga \u6d41\u66a2\u745c\u73c8", "teacher": "Moorthi", "time": "11:00 - 12:15 PM"}, {"room": "\u6566\u5357 6 \u6559\u5ba4", "date": "01 May Sat", "href": "https://www.trueclassbooking.com.tw/member/popup/class-info.aspx?tcl_id=814829", "name": "Aerial Yoga \u7a7a\u4e2d\u745c\u73c8", "teacher": "Melissa", "time": "12:45 - 01:45 PM"}, {"room": "\u6566\u5357 6 \u6559\u5ba4", "date": "01 May Sat", "href": "https://www.trueclassbooking.com.tw/member/popup/class-info.aspx?tcl_id=814830", "name": "Vinyasa Yoga \u6d41\u66a2\u745c\u73c8", "teacher": "Simon Chang", "time": "02:00 - 03:00 PM"}, {"room": "\u6566\u5357 6 \u6559\u5ba4", "date": "01 May Sat", "href": "https://www.trueclassbooking.com.tw/member/popup/class-info.aspx?tcl_id=814831", "name": "Yin Yoga \u9670\u745c\u73c8", "teacher": "Wei Lee", "time": "03:45 - 04:45 PM"}, {"room": "\u6566\u5357 6 \u6559\u5ba4", "date": "01 May Sat", "href": "https://www.trueclassbooking.com.tw/member/popup/class-info.aspx?tcl_id=814832", "name": "Hatha Yoga \u54c8\u9054\u745c\u73c8", "teacher": "Helen", "time": "05:45 - 06:45 PM"}, {"room": "\u6566\u5357 6 \u6559\u5ba4", "date": "02 May Sun", "href": "https://www.trueclassbooking.com.tw/member/popup/class-info.aspx?tcl_id=814833", "name": "Hatha Yoga \u54c8\u9054\u745c\u73c8", "teacher": "YaYa", "time": "10:30 - 11:30 AM"}, {"room": "\u6566\u5357 6 \u6559\u5ba4", "date": "02 May Sun", "href": "https://www.trueclassbooking.com.tw/member/popup/class-info.aspx?tcl_id=814834", "name": "Universal \u5165\u9580", "teacher": "YaYa", "time": "12:30 - 01:30 PM"}, {"room": "\u6566\u5357 6 \u6559\u5ba4", "date": "02 May Sun", "href": "https://www.trueclassbooking.com.tw/member/popup/class-info.aspx?tcl_id=814835", "name": "Universal Yoga \u5bf0\u5b87\u745c\u73c8 1", "teacher": "YaYa", "time": "02:00 - 03:30 PM"}, {"room": "\u6566\u5357 6 \u6559\u5ba4", "date": "02 May Sun", "href": "https://www.trueclassbooking.com.tw/member/popup/class-info.aspx?tcl_id=814836", "name": "Yin Yoga \u9670\u745c\u73c8", "teacher": "YaYa", "time": "03:45 - 04:45 PM"}, {"room": "\u6566\u5357 6 \u6559\u5ba4", "date": "02 May Sun", "href": "https://www.trueclassbooking.com.tw/member/popup/class-info.aspx?tcl_id=814837", "name": "Hatha Yoga \u54c8\u9054\u745c\u73c8", "teacher": "Anita L", "time": "05:30 - 06:30 PM"}, {"room": "\u6566\u5357 7 \u6559\u5ba4", "date": "26 Apr Mon", "href": "https://www.trueclassbooking.com.tw/member/popup/class-info.aspx?tcl_id=814838", "name": "Yoga Tone", "teacher": "Una", "time": "09:00 - 10:00 AM"}, {"room": "\u6566\u5357 7 \u6559\u5ba4", "date": "26 Apr Mon", "href": "https://www.trueclassbooking.com.tw/member/popup/class-info.aspx?tcl_id=814839", "name": "Gentle Yoga \u548c\u7de9\u745c\u73c8", "teacher": "Vinodh", "time": "11:00 - 12:00 PM"}, {"room": "\u6566\u5357 7 \u6559\u5ba4", "date": "26 Apr Mon", "href": "https://www.trueclassbooking.com.tw/member/popup/class-info.aspx?tcl_id=814840", "name": "Iyengar Restorative \u827e\u63da\u683c\u4fee\u5fa9", "teacher": "Yvette", "time": "12:45 - 02:00 PM"}, {"room": "\u6566\u5357 7 \u6559\u5ba4", "date": "26 Apr Mon", "href": "https://www.trueclassbooking.com.tw/member/popup/class-info.aspx?tcl_id=814841", "name": "Vinyasa Intro \u6d41\u66a2\u745c\u73c8\u5165\u9580", "teacher": "Ethan Lee", "time": "03:00 - 04:00 PM"}, {"room": "\u6566\u5357 7 \u6559\u5ba4", "date": "26 Apr Mon", "href": "https://www.trueclassbooking.com.tw/member/popup/class-info.aspx?tcl_id=814842", "name": "Ashtanga Intro. \u963f\u65af\u5766\u52a0\u745c\u73c8\u5165\u9580", "teacher": "Ethan Lee", "time": "04:30 - 05:30 PM"}, {"room": "\u6566\u5357 7 \u6559\u5ba4", "date": "26 Apr Mon", "href": "https://www.trueclassbooking.com.tw/member/popup/class-info.aspx?tcl_id=814843", "name": "Iyengar Basic \u827e\u63da\u683c\u57fa\u790e", "teacher": "Yvette", "time": "06:00 - 07:00 PM"}, {"room": "\u6566\u5357 7 \u6559\u5ba4", "date": "26 Apr Mon", "href": "https://www.trueclassbooking.com.tw/member/popup/class-info.aspx?tcl_id=814844", "name": "\u827e\u63da\u683c \u58c1\u7e69", "teacher": "Yvette", "time": "07:15 - 08:45 PM"}, {"room": "\u6566\u5357 7 \u6559\u5ba4", "date": "27 Apr Tue", "href": "https://www.trueclassbooking.com.tw/member/popup/class-info.aspx?tcl_id=814845", "name": "Hatha Yoga \u54c8\u9054\u745c\u73c8", "teacher": "Andy Tenpa", "time": "09:00 - 10:00 AM"}, {"room": "\u6566\u5357 7 \u6559\u5ba4", "date": "27 Apr Tue", "href": "https://www.trueclassbooking.com.tw/member/popup/class-info.aspx?tcl_id=814846", "name": "Vinyasa Yoga \u6d41\u66a2\u745c\u73c8", "teacher": "Fly H.", "time": "11:00 - 12:00 PM"}, {"room": "\u6566\u5357 7 \u6559\u5ba4", "date": "27 Apr Tue", "href": "https://www.trueclassbooking.com.tw/member/popup/class-info.aspx?tcl_id=814847", "name": "Chair yoga \u6905\u5b50\u745c\u73c8", "teacher": "Fly H.", "time": "02:15 - 03:30 PM"}, {"room": "\u6566\u5357 7 \u6559\u5ba4", "date": "27 Apr Tue", "href": "https://www.trueclassbooking.com.tw/member/popup/class-info.aspx?tcl_id=814848", "name": "\u827e\u63da\u683c \u58c1\u7e69", "teacher": "Yvette", "time": "04:30 - 06:00 PM"}, {"room": "\u6566\u5357 7 \u6559\u5ba4", "date": "27 Apr Tue", "href": "https://www.trueclassbooking.com.tw/member/popup/class-info.aspx?tcl_id=814849", "name": "Hatha Yoga \u54c8\u9054\u745c\u73c8 1", "teacher": "Yvette", "time": "06:15 - 07:15 PM"}, {"room": "\u6566\u5357 7 \u6559\u5ba4", "date": "27 Apr Tue", "href": "https://www.trueclassbooking.com.tw/member/popup/class-info.aspx?tcl_id=814850", "name": "Iyengar Level 1 \u827e\u63da\u683c 1", "teacher": "Anita L", "time": "07:30 - 09:00 PM"}, {"room": "\u6566\u5357 7 \u6559\u5ba4", "date": "28 Apr Wed", "href": "https://www.trueclassbooking.com.tw/member/popup/class-info.aspx?tcl_id=814851", "name": "Gentle Yoga \u548c\u7de9\u745c\u73c8", "teacher": "Coco Wang", "time": "09:00 - 10:00 AM"}, {"room": "\u6566\u5357 7 \u6559\u5ba4", "date": "28 Apr Wed", "href": "https://www.trueclassbooking.com.tw/member/popup/class-info.aspx?tcl_id=814852", "name": "\u52d5\u614b\u4f38\u5c55", "teacher": "William L.", "time": "11:00 - 12:00 PM"}, {"room": "\u6566\u5357 7 \u6559\u5ba4", "date": "28 Apr Wed", "href": "https://www.trueclassbooking.com.tw/member/popup/class-info.aspx?tcl_id=814853", "name": "Hatha Yoga \u54c8\u9054\u745c\u73c8", "teacher": "William L.", "time": "12:30 - 01:30 PM"}, {"room": "\u6566\u5357 7 \u6559\u5ba4", "date": "28 Apr Wed", "href": "https://www.trueclassbooking.com.tw/member/popup/class-info.aspx?tcl_id=814854", "name": "Iyengar Level 1 \u827e\u63da\u683c 1", "teacher": "Yvette", "time": "02:00 - 03:15 PM"}, {"room": "\u6566\u5357 7 \u6559\u5ba4", "date": "28 Apr Wed", "href": "https://www.trueclassbooking.com.tw/member/popup/class-info.aspx?tcl_id=814855", "name": "Iyengar Basic \u827e\u63da\u683c\u57fa\u790e", "teacher": "Yvette", "time": "04:00 - 05:30 PM"}, {"room": "\u6566\u5357 7 \u6559\u5ba4", "date": "28 Apr Wed", "href": "https://www.trueclassbooking.com.tw/member/popup/class-info.aspx?tcl_id=814856", "name": "Chair yoga \u6905\u5b50\u745c\u73c8", "teacher": "Joseph", "time": "06:15 - 07:15 PM"}, {"room": "\u6566\u5357 7 \u6559\u5ba4", "date": "28 Apr Wed", "href": "https://www.trueclassbooking.com.tw/member/popup/class-info.aspx?tcl_id=814857", "name": "Vinyasa Intro \u6d41\u66a2\u745c\u73c8\u5165\u9580", "teacher": "Mei Fen", "time": "07:30 - 08:45 PM"}, {"room": "\u6566\u5357 7 \u6559\u5ba4", "date": "29 Apr Thu", "href": "https://www.trueclassbooking.com.tw/member/popup/class-info.aspx?tcl_id=814858", "name": "Hatha Yoga \u54c8\u9054\u745c\u73c8", "teacher": "Jamie", "time": "07:15 - 08:15 AM"}, {"room": "\u6566\u5357 7 \u6559\u5ba4", "date": "29 Apr Thu", "href": "https://www.trueclassbooking.com.tw/member/popup/class-info.aspx?tcl_id=814859", "name": "Iyengar Basic \u827e\u63da\u683c\u57fa\u790e", "teacher": "Yvette", "time": "10:30 - 11:45 AM"}, {"room": "\u6566\u5357 7 \u6559\u5ba4", "date": "29 Apr Thu", "href": "https://www.trueclassbooking.com.tw/member/popup/class-info.aspx?tcl_id=814861", "name": "Hatha Yoga \u54c8\u9054\u745c\u73c8", "teacher": "Anita L", "time": "03:45 - 04:45 PM"}, {"room": "\u6566\u5357 7 \u6559\u5ba4", "date": "29 Apr Thu", "href": "https://www.trueclassbooking.com.tw/member/popup/class-info.aspx?tcl_id=814862", "name": "Vinyasa Yoga \u6d41\u66a2\u745c\u73c8", "teacher": "Fly H.", "time": "06:00 - 07:00 PM"}, {"room": "\u6566\u5357 7 \u6559\u5ba4", "date": "29 Apr Thu", "href": "https://www.trueclassbooking.com.tw/member/popup/class-info.aspx?tcl_id=814863", "name": "Chair yoga \u6905\u5b50\u745c\u73c8", "teacher": "Fly H.", "time": "07:15 - 08:30 PM"}, {"room": "\u6566\u5357 7 \u6559\u5ba4", "date": "30 Apr Fri", "href": "https://www.trueclassbooking.com.tw/member/popup/class-info.aspx?tcl_id=814864", "name": "Hatha Yoga \u54c8\u9054\u745c\u73c8", "teacher": "Yvette", "time": "07:15 - 08:15 AM"}, {"room": "\u6566\u5357 7 \u6559\u5ba4", "date": "30 Apr Fri", "href": "https://www.trueclassbooking.com.tw/member/popup/class-info.aspx?tcl_id=814865", "name": "\u827e\u63da\u683c \u58c1\u7e69", "teacher": "Yvette", "time": "09:00 - 10:00 AM"}, {"room": "\u6566\u5357 7 \u6559\u5ba4", "date": "30 Apr Fri", "href": "https://www.trueclassbooking.com.tw/member/popup/class-info.aspx?tcl_id=814866", "name": "Vinyasa Yoga2 \u6d41\u66a2\u745c\u73c8 2", "teacher": "Tumai", "time": "11:00 - 12:30 PM"}, {"room": "\u6566\u5357 7 \u6559\u5ba4", "date": "30 Apr Fri", "href": "https://www.trueclassbooking.com.tw/member/popup/class-info.aspx?tcl_id=814867", "name": "Iyengar Intro \u827e\u694a\u683c\u5165\u9580", "teacher": "Joy", "time": "02:30 - 03:30 PM"}, {"room": "\u6566\u5357 7 \u6559\u5ba4", "date": "30 Apr Fri", "href": "https://www.trueclassbooking.com.tw/member/popup/class-info.aspx?tcl_id=814868", "name": "Chair yoga \u6905\u5b50\u745c\u73c8", "teacher": "Joy", "time": "03:45 - 04:45 PM"}, {"room": "\u6566\u5357 7 \u6559\u5ba4", "date": "30 Apr Fri", "href": "https://www.trueclassbooking.com.tw/member/popup/class-info.aspx?tcl_id=814869", "name": "Vinyasa Yoga \u6d41\u66a2\u745c\u73c8", "teacher": "Fly H.", "time": "06:00 - 07:00 PM"}, {"room": "\u6566\u5357 7 \u6559\u5ba4", "date": "30 Apr Fri", "href": "https://www.trueclassbooking.com.tw/member/popup/class-info.aspx?tcl_id=814870", "name": "Hatha Yoga 2 \u54c8\u9054\u745c\u73c8 2", "teacher": "Fly H.", "time": "07:15 - 08:45 PM"}, {"room": "\u6566\u5357 7 \u6559\u5ba4", "date": "01 May Sat", "href": "https://www.trueclassbooking.com.tw/member/popup/class-info.aspx?tcl_id=814871", "name": "\u5973\u6027\u6ecb\u990a", "teacher": "Joy", "time": "10:45 - 12:00 PM"}, {"room": "\u6566\u5357 7 \u6559\u5ba4", "date": "01 May Sat", "href": "https://www.trueclassbooking.com.tw/member/popup/class-info.aspx?tcl_id=814872", "name": "Iyengar Level 1 \u827e\u63da\u683c 1", "teacher": "Anita L", "time": "02:15 - 03:45 PM"}, {"room": "\u6566\u5357 7 \u6559\u5ba4", "date": "01 May Sat", "href": "https://www.trueclassbooking.com.tw/member/popup/class-info.aspx?tcl_id=814873", "name": "Iyengar Level 2 \u827e\u63da\u683c 2", "teacher": "Anita L", "time": "04:00 - 05:30 PM"}, {"room": "\u6566\u5357 7 \u6559\u5ba4", "date": "01 May Sat", "href": "https://www.trueclassbooking.com.tw/member/popup/class-info.aspx?tcl_id=814874", "name": "Iyengar Restorative \u827e\u63da\u683c\u4fee\u5fa9", "teacher": "Anita L", "time": "06:00 - 07:15 PM"}, {"room": "\u6566\u5357 7 \u6559\u5ba4", "date": "02 May Sun", "href": "https://www.trueclassbooking.com.tw/member/popup/class-info.aspx?tcl_id=814876", "name": "Chair yoga \u6905\u5b50\u745c\u73c8", "teacher": "Joseph", "time": "02:00 - 03:15 PM"}, {"room": "\u6566\u5357 7 \u6559\u5ba4", "date": "02 May Sun", "href": "https://www.trueclassbooking.com.tw/member/popup/class-info.aspx?tcl_id=814877", "name": "Restorative Yoga \u4fee\u5fa9\u745c\u73c8", "teacher": "Joseph", "time": "04:00 - 05:00 PM"}, {"room": "\u6566\u5357 7 \u6559\u5ba4", "date": "02 May Sun", "href": "https://www.trueclassbooking.com.tw/member/popup/class-info.aspx?tcl_id=814878", "name": "Iyengar Basic \u827e\u63da\u683c\u57fa\u790e", "teacher": "Anita L", "time": "06:45 - 08:00 PM"}, {"room": "\u6566\u5357 9 \u6559\u5ba4", "date": "26 Apr Mon", "href": "https://www.trueclassbooking.com.tw/member/popup/class-info.aspx?tcl_id=814879", "name": "Hot Yoga \u71b1\u745c\u73c8", "teacher": "Vinodh", "time": "12:15 - 01:15 PM"}, {"room": "\u6566\u5357 9 \u6559\u5ba4", "date": "26 Apr Mon", "href": "https://www.trueclassbooking.com.tw/member/popup/class-info.aspx?tcl_id=814880", "name": "Hatha Yoga \u54c8\u9054\u745c\u73c8", "teacher": "Coco Wang", "time": "02:15 - 03:15 PM"}, {"room": "\u6566\u5357 9 \u6559\u5ba4", "date": "26 Apr Mon", "href": "https://www.trueclassbooking.com.tw/member/popup/class-info.aspx?tcl_id=814881", "name": "Warm Stretch \u6eab\u548c\u4f38\u5c55", "teacher": "Coco Wang", "time": "05:15 - 06:15 PM"}, {"room": "\u6566\u5357 9 \u6559\u5ba4", "date": "26 Apr Mon", "href": "https://www.trueclassbooking.com.tw/member/popup/class-info.aspx?tcl_id=814882", "name": "Hot Yoga \u71b1\u745c\u73c8", "teacher": "Tumai", "time": "06:45 - 07:45 PM"}, {"room": "\u6566\u5357 9 \u6559\u5ba4", "date": "26 Apr Mon", "href": "https://www.trueclassbooking.com.tw/member/popup/class-info.aspx?tcl_id=814883", "name": "Warm Stretch \u6eab\u548c\u4f38\u5c55", "teacher": "Fly H.", "time": "08:45 - 09:45 PM"}, {"room": "\u6566\u5357 9 \u6559\u5ba4", "date": "27 Apr Tue", "href": "https://www.trueclassbooking.com.tw/member/popup/class-info.aspx?tcl_id=814884", "name": "Warm Stretch \u6eab\u548c\u4f38\u5c55", "teacher": "Mei Wang", "time": "12:15 - 01:15 PM"}, {"room": "\u6566\u5357 9 \u6559\u5ba4", "date": "27 Apr Tue", "href": "https://www.trueclassbooking.com.tw/member/popup/class-info.aspx?tcl_id=814885", "name": "Core Yoga \u6838\u5fc3\u745c\u73c8", "teacher": "Mei Wang", "time": "02:00 - 03:00 PM"}, {"room": "\u6566\u5357 9 \u6559\u5ba4", "date": "27 Apr Tue", "href": "https://www.trueclassbooking.com.tw/member/popup/class-info.aspx?tcl_id=814886", "name": "Warm Stretch \u6eab\u548c\u4f38\u5c55", "teacher": "Una", "time": "04:00 - 05:00 PM"}, {"room": "\u6566\u5357 9 \u6559\u5ba4", "date": "27 Apr Tue", "href": "https://www.trueclassbooking.com.tw/member/popup/class-info.aspx?tcl_id=814887", "name": "Hot Flow \u71b1\u52d5", "teacher": "Andrew B.", "time": "06:45 - 07:45 PM"}, {"room": "\u6566\u5357 9 \u6559\u5ba4", "date": "27 Apr Tue", "href": "https://www.trueclassbooking.com.tw/member/popup/class-info.aspx?tcl_id=814888", "name": "Hot Yoga \u71b1\u745c\u73c8", "teacher": "Andrew B.", "time": "08:15 - 09:15 PM"}, {"room": "\u6566\u5357 9 \u6559\u5ba4", "date": "28 Apr Wed", "href": "https://www.trueclassbooking.com.tw/member/popup/class-info.aspx?tcl_id=814889", "name": "Vinyasa Intro \u6d41\u66a2\u745c\u73c8\u5165\u9580", "teacher": "Tumai", "time": "09:30 - 10:30 AM"}, {"room": "\u6566\u5357 9 \u6559\u5ba4", "date": "28 Apr Wed", "href": "https://www.trueclassbooking.com.tw/member/popup/class-info.aspx?tcl_id=814890", "name": "Hot Flow \u71b1\u52d5", "teacher": "Carolyn", "time": "12:15 - 01:15 PM"}, {"room": "\u6566\u5357 9 \u6559\u5ba4", "date": "28 Apr Wed", "href": "https://www.trueclassbooking.com.tw/member/popup/class-info.aspx?tcl_id=814891", "name": "Hatha Yoga \u54c8\u9054\u745c\u73c8", "teacher": "Priya", "time": "03:00 - 04:00 PM"}, {"room": "\u6566\u5357 9 \u6559\u5ba4", "date": "28 Apr Wed", "href": "https://www.trueclassbooking.com.tw/member/popup/class-info.aspx?tcl_id=814892", "name": "Gentle Yoga \u548c\u7de9\u745c\u73c8", "teacher": "Priya", "time": "04:30 - 05:30 PM"}, {"room": "\u6566\u5357 9 \u6559\u5ba4", "date": "28 Apr Wed", "href": "https://www.trueclassbooking.com.tw/member/popup/class-info.aspx?tcl_id=814893", "name": "Hot Yoga \u71b1\u745c\u73c8", "teacher": "Ethan Lee", "time": "06:45 - 07:45 PM"}, {"room": "\u6566\u5357 9 \u6559\u5ba4", "date": "28 Apr Wed", "href": "https://www.trueclassbooking.com.tw/member/popup/class-info.aspx?tcl_id=814894", "name": "Hot Flow \u71b1\u52d5", "teacher": "Andy Tenpa", "time": "08:30 - 09:30 PM"}, {"room": "\u6566\u5357 9 \u6559\u5ba4", "date": "29 Apr Thu", "href": "https://www.trueclassbooking.com.tw/member/popup/class-info.aspx?tcl_id=814895", "name": "Hatha Yoga \u54c8\u9054\u745c\u73c8", "teacher": "Mei Wang", "time": "09:30 - 10:30 AM"}, {"room": "\u6566\u5357 9 \u6559\u5ba4", "date": "29 Apr Thu", "href": "https://www.trueclassbooking.com.tw/member/popup/class-info.aspx?tcl_id=814896", "name": "Warm Stretch \u6eab\u548c\u4f38\u5c55", "teacher": "Mei Wang", "time": "12:15 - 01:15 PM"}, {"room": "\u6566\u5357 9 \u6559\u5ba4", "date": "29 Apr Thu", "href": "https://www.trueclassbooking.com.tw/member/popup/class-info.aspx?tcl_id=814897", "name": "Warm Stretch \u6eab\u548c\u4f38\u5c55", "teacher": "Andy Tenpa", "time": "05:00 - 06:00 PM"}, {"room": "\u6566\u5357 9 \u6559\u5ba4", "date": "29 Apr Thu", "href": "https://www.trueclassbooking.com.tw/member/popup/class-info.aspx?tcl_id=814898", "name": "Hot Yoga \u71b1\u745c\u73c8", "teacher": "Andrew B.", "time": "06:45 - 07:45 PM"}, {"room": "\u6566\u5357 9 \u6559\u5ba4", "date": "29 Apr Thu", "href": "https://www.trueclassbooking.com.tw/member/popup/class-info.aspx?tcl_id=814899", "name": "Warm Stretch \u6eab\u548c\u4f38\u5c55", "teacher": "Andrew B.", "time": "08:15 - 09:15 PM"}, {"room": "\u6566\u5357 9 \u6559\u5ba4", "date": "30 Apr Fri", "href": "https://www.trueclassbooking.com.tw/member/popup/class-info.aspx?tcl_id=814781", "name": "Vinyasa Intro \u6d41\u66a2\u745c\u73c8\u5165\u9580", "teacher": "Tumai", "time": "09:30 - 10:30 AM"}, {"room": "\u6566\u5357 9 \u6559\u5ba4", "date": "30 Apr Fri", "href": "https://www.trueclassbooking.com.tw/member/popup/class-info.aspx?tcl_id=814900", "name": "Warm Stretch \u6eab\u548c\u4f38\u5c55", "teacher": "Una", "time": "12:15 - 01:15 PM"}, {"room": "\u6566\u5357 9 \u6559\u5ba4", "date": "30 Apr Fri", "href": "https://www.trueclassbooking.com.tw/member/popup/class-info.aspx?tcl_id=814901", "name": "Hot Yoga \u71b1\u745c\u73c8", "teacher": "Ellen", "time": "03:00 - 04:00 PM"}, {"room": "\u6566\u5357 9 \u6559\u5ba4", "date": "30 Apr Fri", "href": "https://www.trueclassbooking.com.tw/member/popup/class-info.aspx?tcl_id=814902", "name": "Warm Stretch \u6eab\u548c\u4f38\u5c55", "teacher": "Andy Tenpa", "time": "05:15 - 06:15 PM"}, {"room": "\u6566\u5357 9 \u6559\u5ba4", "date": "30 Apr Fri", "href": "https://www.trueclassbooking.com.tw/member/popup/class-info.aspx?tcl_id=814903", "name": "Hot Flow \u71b1\u52d5", "teacher": "Andy Tenpa", "time": "06:45 - 07:45 PM"}, {"room": "\u6566\u5357 9 \u6559\u5ba4", "date": "30 Apr Fri", "href": "https://www.trueclassbooking.com.tw/member/popup/class-info.aspx?tcl_id=814904", "name": "Warm Stretch \u6eab\u548c\u4f38\u5c55", "teacher": "Fly H.", "time": "09:00 - 10:00 PM"}, {"room": "\u6566\u5357 9 \u6559\u5ba4", "date": "01 May Sat", "href": "https://www.trueclassbooking.com.tw/member/popup/class-info.aspx?tcl_id=814905", "name": "Ashtanga 2 & Conference", "teacher": "Simon Chang", "time": "09:00 - 11:00 AM"}, {"room": "\u6566\u5357 9 \u6559\u5ba4", "date": "01 May Sat", "href": "https://www.trueclassbooking.com.tw/member/popup/class-info.aspx?tcl_id=814906", "name": "Hot Yoga \u71b1\u745c\u73c8", "teacher": "Andrew B.", "time": "12:00 - 01:00 PM"}, {"room": "\u6566\u5357 9 \u6559\u5ba4", "date": "01 May Sat", "href": "https://www.trueclassbooking.com.tw/member/popup/class-info.aspx?tcl_id=814907", "name": "Gentle Yoga \u548c\u7de9\u745c\u73c8", "teacher": "Coco Wang", "time": "03:30 - 04:30 PM"}, {"room": "\u6566\u5357 9 \u6559\u5ba4", "date": "01 May Sat", "href": "https://www.trueclassbooking.com.tw/member/popup/class-info.aspx?tcl_id=814908", "name": "Hot Yoga \u71b1\u745c\u73c8", "teacher": "Mei Fen", "time": "06:45 - 07:45 PM"}, {"room": "\u6566\u5357 9 \u6559\u5ba4", "date": "02 May Sun", "href": "https://www.trueclassbooking.com.tw/member/popup/class-info.aspx?tcl_id=814909", "name": "Warm Stretch \u6eab\u548c\u4f38\u5c55", "teacher": "Una", "time": "10:15 - 11:15 AM"}, {"room": "\u6566\u5357 9 \u6559\u5ba4", "date": "02 May Sun", "href": "https://www.trueclassbooking.com.tw/member/popup/class-info.aspx?tcl_id=814910", "name": "Hot Yoga \u71b1\u745c\u73c8", "teacher": "Carolyn", "time": "12:15 - 01:15 PM"}, {"room": "\u6566\u5357 9 \u6559\u5ba4", "date": "02 May Sun", "href": "https://www.trueclassbooking.com.tw/member/popup/class-info.aspx?tcl_id=814911", "name": "Hot Flow \u71b1\u52d5", "teacher": "Carolyn", "time": "02:30 - 03:30 PM"}, {"room": "\u6566\u5357 9 \u6559\u5ba4", "date": "02 May Sun", "href": "https://www.trueclassbooking.com.tw/member/popup/class-info.aspx?tcl_id=814912", "name": "\u76ae\u62c9\u63d0\u65af\u80fd\u91cf\u68d2", "teacher": "Joyce", "time": "04:15 - 05:15 PM"}]